odoo/addons/purchase_stock_ubl/README.rst
odoo/addons/purchase_stock_ubl/__init__.py
odoo/addons/purchase_stock_ubl/__manifest__.py
odoo/addons/purchase_stock_ubl/i18n/purchase_stock_ubl.pot
odoo/addons/purchase_stock_ubl/models/__init__.py
odoo/addons/purchase_stock_ubl/models/purchase.py
odoo/addons/purchase_stock_ubl/readme/CONTRIBUTORS.rst
odoo/addons/purchase_stock_ubl/readme/DESCRIPTION.rst
odoo/addons/purchase_stock_ubl/static/description/icon.png
odoo/addons/purchase_stock_ubl/static/description/index.html
odoo/addons/purchase_stock_ubl/tests/__init__.py
odoo/addons/purchase_stock_ubl/tests/test_purchase_order.py
odoo13_addon_purchase_stock_ubl-13.0.1.1.1.dist-info/METADATA
odoo13_addon_purchase_stock_ubl-13.0.1.1.1.dist-info/WHEEL
odoo13_addon_purchase_stock_ubl-13.0.1.1.1.dist-info/top_level.txt
odoo13_addon_purchase_stock_ubl-13.0.1.1.1.dist-info/RECORD
